memobird_agent/__init__.py
memobird_agent/config.py
memobird_agent/security.py
memobird_agent/script/__init__.py
memobird_agent/script/document.py
memobird_agent/script/machine_monitor.py
memobird_agent/script/service_monitor.py
memobird_agent/script/transmission_monitor.py
memobird_agent-2.1.12.dist-info/METADATA
memobird_agent-2.1.12.dist-info/RECORD
memobird_agent-2.1.12.dist-info/WHEEL
memobird_agent-2.1.12.dist-info/entry_points.txt
memobird_agent-2.1.12.dist-info/top_level.txt
